requisite
