Metadata-Version: 1.0
Name: requisite
Version: 0.1.3
Summary: Requisite downloads python packages from a requirements.txt file and uploads them to your private PyPI server
Home-page: http://github.com/samuraisam/requisite
Author: Samuel Sutch
Author-email: sam@altertap.com
License: MIT
Keywords: easy_install distutils setuptools egg virtualenv pip
Platform: UNKNOWN
Classifier: Development Status :: 3 - Alpha
Classifier: Intended Audience :: Developers
Classifier: License :: OSI Approved :: MIT License
Classifier: Topic :: Software Development :: Build Tools
